[{"win_team_name":"海の幸","win_team_mvp":"ちひろ."},{"win_team_name":"海の幸","win_team_mvp":"かまぼこ"},{"win_team_name":"山の幸","win_team_mvp":"アーク"},{"win_team_name":"海の幸","win_team_mvp":"hiori"},{"win_team_name":"山の幸","win_team_mvp":"♪かめむっし～♪"},{"win_team_name":"海の幸","win_team_mvp":"ウト(・´ワ・`)⊃"},{"win_team_name":"山の幸","win_team_mvp":"たかお"},{"win_team_name":"海の幸","win_team_mvp":"まろやか"},{"win_team_name":"山の幸","win_team_mvp":"どく"},{"win_team_name":"山の幸","win_team_mvp":"たこやき"},{"win_team_name":"海の幸","win_team_mvp":"ナミキ"},{"win_team_name":"山の幸","win_team_mvp":"ひとくん"},{"win_team_name":"山の幸","win_team_mvp":"しんくう.Regen"},{"win_team_name":"海の幸","win_team_mvp":"キクフジ"},{"win_team_name":"山の幸","win_team_mvp":"HETARE"},{"win_team_name":"海の幸","win_team_mvp":"ちーたん"},{"win_team_name":"海の幸","win_team_mvp":"ソルト"},{"win_team_name":"海の幸","win_team_mvp":"saezuri."},{"win_team_name":"海の幸","win_team_mvp":"RIKU"},{"win_team_name":"海の幸","win_team_mvp":"Gallon#spk"},{"win_team_name":"海の幸","win_team_mvp":"Linglinq"},{"win_team_name":"海の幸","win_team_mvp":"やま"},{"win_team_name":"山の幸","win_team_mvp":"グッドリッジ"},{"win_team_name":"山の幸","win_team_mvp":"かず"},{"win_team_name":"山の幸","win_team_mvp":"\u003cよう.Regen\u003e"},{"win_team_name":"海の幸","win_team_mvp":"きのせい"},{"win_team_name":"山の幸","win_team_mvp":"こいけくん"},{"win_team_name":"海の幸","win_team_mvp":"Hamburger"},{"win_team_name":"山の幸","win_team_mvp":"ゆい"},{"win_team_name":"海の幸","win_team_mvp":"おとうさん"},{"win_team_name":"海の幸","win_team_mvp":"ままち"},{"win_team_name":"山の幸","win_team_mvp":"まま"},{"win_team_name":"海の幸","win_team_mvp":"eternal(☆)"},{"win_team_name":"海の幸","win_team_mvp":"ルマミラ"},{"win_team_name":"山の幸","win_team_mvp":"とうふちゃん"},{"win_team_name":"山の幸","win_team_mvp":"HINATA"},{"win_team_name":"海の幸","win_team_mvp":"うんこ"},{"win_team_name":"海の幸","win_team_mvp":"ざく"},{"win_team_name":"山の幸","win_team_mvp":"そなたはにんげんだ!"},{"win_team_name":"海の幸","win_team_mvp":"あいぽよ"},{"win_team_name":"山の幸","win_team_mvp":"なおき"},{"win_team_name":"山の幸","win_team_mvp":"マーガリン"},{"win_team_name":"海の幸","win_team_mvp":"のんのん"},{"win_team_name":"海の幸","win_team_mvp":"õÿåśśäň"},{"win_team_name":"海の幸","win_team_mvp":"トーテムポール"},{"win_team_name":"山の幸","win_team_mvp":"あんぜんせんし"},{"win_team_name":"山の幸","win_team_mvp":"Ashley"},{"win_team_name":"山の幸","win_team_mvp":"しょう"},{"win_team_name":"海の幸","win_team_mvp":"ミケ"},{"win_team_name":"海の幸","win_team_mvp":"ぬりべんきょうちゅう"},{"win_team_name":"海の幸","win_team_mvp":"しゃくれあご"},{"win_team_name":"山の幸","win_team_mvp":"ハラケイ"},{"win_team_name":"山の幸","win_team_mvp":"きなこ"},{"win_team_name":"海の幸","win_team_mvp":"うご"},{"win_team_name":"山の幸","win_team_mvp":"せんぱんふかいひb"},{"win_team_name":"山の幸","win_team_mvp":"Hinata"},{"win_team_name":"山の幸","win_team_mvp":"アホのイヨカン"},{"win_team_name":"山の幸","win_team_mvp":"Yuki-Efo"},{"win_team_name":"山の幸","win_team_mvp":"H\u0026Y\u0026M"},{"win_team_name":"海の幸","win_team_mvp":"クルマ"},{"win_team_name":"山の幸","win_team_mvp":"はるや"},{"win_team_name":"海の幸","win_team_mvp":"うみき"},{"win_team_name":"海の幸","win_team_mvp":"ゆうき"},{"win_team_name":"海の幸","win_team_mvp":"のめ"},{"win_team_name":"海の幸","win_team_mvp":"くろねこ"},{"win_team_name":"山の幸","win_team_mvp":"ナバール"},{"win_team_name":"海の幸","win_team_mvp":"ミキイカ(・ー・)"},{"win_team_name":"山の幸","win_team_mvp":"スパショやり.InW"},{"win_team_name":"海の幸","win_team_mvp":"シュリ"},{"win_team_name":"山の幸","win_team_mvp":"ゆさゆさ"},{"win_team_name":"海の幸","win_team_mvp":"   DK    "},{"win_team_name":"山の幸","win_team_mvp":"junior∵※ゲス"},{"win_team_name":"山の幸","win_team_mvp":"わさを"},{"win_team_name":"海の幸","win_team_mvp":"りんたそ"},{"win_team_name":"山の幸","win_team_mvp":"ピサのしゃとう"},{"win_team_name":"山の幸","win_team_mvp":"もっちー　ache."},{"win_team_name":"海の幸","win_team_mvp":"TISATO"},{"win_team_name":"海の幸","win_team_mvp":"こっすん"},{"win_team_name":"山の幸","win_team_mvp":"mochi"},{"win_team_name":"海の幸","win_team_mvp":"どせいさん"},{"win_team_name":"海の幸","win_team_mvp":"K.K"},{"win_team_name":"海の幸","win_team_mvp":"ムメイ"},{"win_team_name":"山の幸","win_team_mvp":"Chiroru/L¢"},{"win_team_name":"山の幸","win_team_mvp":"Kくん(^∀^)/"},{"win_team_name":"海の幸","win_team_mvp":"A24_ひえぴた"},{"win_team_name":"山の幸","win_team_mvp":"センパンマン"},{"win_team_name":"海の幸","win_team_mvp":"は。"},{"win_team_name":"海の幸","win_team_mvp":"⊂⊂( ⌒ω⌒)⊃⊃"},{"win_team_name":"山の幸","win_team_mvp":"ジバニャン"},{"win_team_name":"山の幸","win_team_mvp":"せんぱい"},{"win_team_name":"山の幸","win_team_mvp":"おだ"},{"win_team_name":"山の幸","win_team_mvp":"アンナ"}]