[{"win_team_name":"イカ","win_team_mvp":"こん"},{"win_team_name":"イカ","win_team_mvp":"PGモズク"},{"win_team_name":"イカ","win_team_mvp":"ひら"},{"win_team_name":"タコ","win_team_mvp":"KIKI"},{"win_team_name":"タコ","win_team_mvp":"しろる"},{"win_team_name":"タコ","win_team_mvp":"アカリ"},{"win_team_name":"タコ","win_team_mvp":"てんむす〃・ω・〃"},{"win_team_name":"タコ","win_team_mvp":"ヨークベニマル"},{"win_team_name":"タコ","win_team_mvp":"とも"},{"win_team_name":"タコ","win_team_mvp":"ちゃぎ"},{"win_team_name":"タコ","win_team_mvp":"まさや"},{"win_team_name":"イカ","win_team_mvp":"タツキング"},{"win_team_name":"タコ","win_team_mvp":"たか"},{"win_team_name":"イカ","win_team_mvp":"みやこ"},{"win_team_name":"イカ","win_team_mvp":"　"},{"win_team_name":"イカ","win_team_mvp":"イカのポコテン"},{"win_team_name":"イカ","win_team_mvp":"Mtoto"},{"win_team_name":"イカ","win_team_mvp":"asaki193"},{"win_team_name":"タコ","win_team_mvp":"バニラ"},{"win_team_name":"タコ","win_team_mvp":"(´・ω・`)"},{"win_team_name":"タコ","win_team_mvp":"Ichaival"},{"win_team_name":"タコ","win_team_mvp":"おじぽっくる"},{"win_team_name":"イカ","win_team_mvp":"ネコさん"},{"win_team_name":"タコ","win_team_mvp":"ab-boy"},{"win_team_name":"タコ","win_team_mvp":"ソラネス*ゆきぎつね"},{"win_team_name":"イカ","win_team_mvp":"はるひ"},{"win_team_name":"タコ","win_team_mvp":"とみゃん"},{"win_team_name":"イカ","win_team_mvp":"イノシシパーク"},{"win_team_name":"タコ","win_team_mvp":"したら　せり"},{"win_team_name":"タコ","win_team_mvp":"りでる"},{"win_team_name":"タコ","win_team_mvp":"きよ♪"},{"win_team_name":"イカ","win_team_mvp":"れじゅめせんし"},{"win_team_name":"タコ","win_team_mvp":"もちこ"},{"win_team_name":"タコ","win_team_mvp":"イロイロなイロ"},{"win_team_name":"イカ","win_team_mvp":"あめ"},{"win_team_name":"イカ","win_team_mvp":"あれ"},{"win_team_name":"タコ","win_team_mvp":"みさと"},{"win_team_name":"タコ","win_team_mvp":"ごまだんご"},{"win_team_name":"イカ","win_team_mvp":"めっと"},{"win_team_name":"タコ","win_team_mvp":"ろすけ"},{"win_team_name":"タコ","win_team_mvp":"さしみ(タコ)"},{"win_team_name":"タコ","win_team_mvp":"SPRC*リミナ"},{"win_team_name":"タコ","win_team_mvp":"たける"},{"win_team_name":"タコ","win_team_mvp":"はこだてこがね"},{"win_team_name":"イカ","win_team_mvp":"はると"},{"win_team_name":"イカ","win_team_mvp":"がらパンツごし"},{"win_team_name":"タコ","win_team_mvp":"ボールドりん"},{"win_team_name":"イカ","win_team_mvp":"たいせい"},{"win_team_name":"タコ","win_team_mvp":"Kiyoharyu"},{"win_team_name":"タコ","win_team_mvp":"やさしいぶきやま"},{"win_team_name":"タコ","win_team_mvp":"†ひろと†"},{"win_team_name":"タコ","win_team_mvp":"ろんじゃですぞwww"},{"win_team_name":"イカ","win_team_mvp":"KY"},{"win_team_name":"タコ","win_team_mvp":"astaroth"},{"win_team_name":"イカ","win_team_mvp":"さあちまん"},{"win_team_name":"タコ","win_team_mvp":"しゅうめい"},{"win_team_name":"イカ","win_team_mvp":"Gsan"},{"win_team_name":"イカ","win_team_mvp":"ともぞう"},{"win_team_name":"イカ","win_team_mvp":"しの"},{"win_team_name":"タコ","win_team_mvp":"a"},{"win_team_name":"タコ","win_team_mvp":"KENTA"},{"win_team_name":"イカ","win_team_mvp":"ドケダ・グンミーチャ"},{"win_team_name":"タコ","win_team_mvp":"ミトスパ"},{"win_team_name":"イカ","win_team_mvp":"しん"},{"win_team_name":"タコ","win_team_mvp":"NTM"},{"win_team_name":"タコ","win_team_mvp":"ゆうせい"},{"win_team_name":"イカ","win_team_mvp":"まーぼう"},{"win_team_name":"イカ","win_team_mvp":"がく"},{"win_team_name":"タコ","win_team_mvp":"ろいすっち"},{"win_team_name":"イカ","win_team_mvp":"Mako.Na-na"},{"win_team_name":"タコ","win_team_mvp":"ぷれんてい"},{"win_team_name":"イカ","win_team_mvp":"しん"},{"win_team_name":"イカ","win_team_mvp":"☆akkari～n☆"},{"win_team_name":"タコ","win_team_mvp":"ゆっくりやち～"},{"win_team_name":"イカ","win_team_mvp":"たいさ"},{"win_team_name":"タコ","win_team_mvp":"あいとゆうきとのきみ"},{"win_team_name":"タコ","win_team_mvp":"あふろぼんばー"},{"win_team_name":"イカ","win_team_mvp":"はなやつ"},{"win_team_name":"タコ","win_team_mvp":"きゃり"},{"win_team_name":"タコ","win_team_mvp":"ちゃーはん"},{"win_team_name":"タコ","win_team_mvp":"けっけ"},{"win_team_name":"タコ","win_team_mvp":"アヒルだーね"},{"win_team_name":"タコ","win_team_mvp":".com"},{"win_team_name":"タコ","win_team_mvp":"マグロ"},{"win_team_name":"イカ","win_team_mvp":"ロロノア　ゾロ"},{"win_team_name":"イカ","win_team_mvp":"もっちりノンタ"},{"win_team_name":"タコ","win_team_mvp":"クーリィ"},{"win_team_name":"タコ","win_team_mvp":"ニッシー"},{"win_team_name":"イカ","win_team_mvp":"そがっち"},{"win_team_name":"タコ","win_team_mvp":"βてル#sp.IG"},{"win_team_name":"タコ","win_team_mvp":"てけりぽ"}]