[{"win_team_name":"ツナマヨ","win_team_mvp":"ホタマル"},{"win_team_name":"しゃけ","win_team_mvp":"RN∵あき"},{"win_team_name":"しゃけ","win_team_mvp":"ラン"},{"win_team_name":"ツナマヨ","win_team_mvp":"ばーど"},{"win_team_name":"ツナマヨ","win_team_mvp":"トーラス_ふじにゃー"},{"win_team_name":"しゃけ","win_team_mvp":"そーちゃん"},{"win_team_name":"しゃけ","win_team_mvp":"まつのとぅーん"},{"win_team_name":"ツナマヨ","win_team_mvp":"りゅうちイカ"},{"win_team_name":"ツナマヨ","win_team_mvp":"にーぱんまん"},{"win_team_name":"しゃけ","win_team_mvp":"whiterabit"},{"win_team_name":"しゃけ","win_team_mvp":"まだまだべいべー"},{"win_team_name":"しゃけ","win_team_mvp":"NXGH74"},{"win_team_name":"しゃけ","win_team_mvp":"ゆー"},{"win_team_name":"ツナマヨ","win_team_mvp":"なんぴょんちーくわー"},{"win_team_name":"ツナマヨ","win_team_mvp":"(´・ω・` )"},{"win_team_name":"しゃけ","win_team_mvp":"だい"},{"win_team_name":"しゃけ","win_team_mvp":"こめつぶ"},{"win_team_name":"ツナマヨ","win_team_mvp":"ゆうた"},{"win_team_name":"しゃけ","win_team_mvp":"おいしいハンバーグ"},{"win_team_name":"しゃけ","win_team_mvp":"アカシ"},{"win_team_name":"しゃけ","win_team_mvp":"しゅうすけ"},{"win_team_name":"しゃけ","win_team_mvp":"ほむらまんじゅう"},{"win_team_name":"しゃけ","win_team_mvp":"ガブリエル"},{"win_team_name":"しゃけ","win_team_mvp":"だがしやよっちゃん*"},{"win_team_name":"しゃけ","win_team_mvp":"カメレオン「HTS」"},{"win_team_name":"しゃけ","win_team_mvp":"ブラックサンダー"},{"win_team_name":"しゃけ","win_team_mvp":"はやと"},{"win_team_name":"しゃけ","win_team_mvp":"うっちー"},{"win_team_name":"しゃけ","win_team_mvp":"ぷぴこ"},{"win_team_name":"ツナマヨ","win_team_mvp":"ブラジル"},{"win_team_name":"しゃけ","win_team_mvp":"★KAYU★"},{"win_team_name":"しゃけ","win_team_mvp":"あい"},{"win_team_name":"ツナマヨ","win_team_mvp":"しょうま"},{"win_team_name":"しゃけ","win_team_mvp":"りく"},{"win_team_name":"ツナマヨ","win_team_mvp":"こっちゃん"},{"win_team_name":"しゃけ","win_team_mvp":"LMG\"_ツッキー"},{"win_team_name":"しゃけ","win_team_mvp":"てんま"},{"win_team_name":"しゃけ","win_team_mvp":"しろぶた"},{"win_team_name":"しゃけ","win_team_mvp":"たいき"},{"win_team_name":"しゃけ","win_team_mvp":"Mi0"},{"win_team_name":"しゃけ","win_team_mvp":"こたろう"},{"win_team_name":"ツナマヨ","win_team_mvp":"Kota"},{"win_team_name":"しゃけ","win_team_mvp":"クラクラ"},{"win_team_name":"ツナマヨ","win_team_mvp":"みかん"},{"win_team_name":"しゃけ","win_team_mvp":"ひなた"},{"win_team_name":"しゃけ","win_team_mvp":"りくと"},{"win_team_name":"しゃけ","win_team_mvp":"Taiga"},{"win_team_name":"しゃけ","win_team_mvp":"しゅん"},{"win_team_name":"ツナマヨ","win_team_mvp":"キョッピー"},{"win_team_name":"しゃけ","win_team_mvp":"ゆゆ"},{"win_team_name":"しゃけ","win_team_mvp":"Manekiタイガー"},{"win_team_name":"ツナマヨ","win_team_mvp":"ほゆゆ"},{"win_team_name":"しゃけ","win_team_mvp":"ふうか"},{"win_team_name":"ツナマヨ","win_team_mvp":"REO#れお"},{"win_team_name":"しゃけ","win_team_mvp":"レモンティー"},{"win_team_name":"ツナマヨ","win_team_mvp":"ヒデパパ"},{"win_team_name":"ツナマヨ","win_team_mvp":"にんにくマシマシ"},{"win_team_name":"ツナマヨ","win_team_mvp":"ミニ"},{"win_team_name":"ツナマヨ","win_team_mvp":"りゅうすけ"},{"win_team_name":"しゃけ","win_team_mvp":"あけめん♪"},{"win_team_name":"ツナマヨ","win_team_mvp":"キンカンZ"},{"win_team_name":"ツナマヨ","win_team_mvp":"あゆん(なす)"},{"win_team_name":"しゃけ","win_team_mvp":"ひろき"},{"win_team_name":"しゃけ","win_team_mvp":"イカ"},{"win_team_name":"ツナマヨ","win_team_mvp":"りー"},{"win_team_name":"ツナマヨ","win_team_mvp":"A.S/"},{"win_team_name":"しゃけ","win_team_mvp":"きぼりのくまとさけ"},{"win_team_name":"ツナマヨ","win_team_mvp":"だいち"},{"win_team_name":"しゃけ","win_team_mvp":"ふたば"},{"win_team_name":"しゃけ","win_team_mvp":"れん!"},{"win_team_name":"しゃけ","win_team_mvp":"じゅーしーまちゅりん"},{"win_team_name":"しゃけ","win_team_mvp":"Rっちょ!!!!!!"},{"win_team_name":"ツナマヨ","win_team_mvp":"なお"},{"win_team_name":"ツナマヨ","win_team_mvp":"ギリシャネコ"},{"win_team_name":"しゃけ","win_team_mvp":"そうちゃん"},{"win_team_name":"ツナマヨ","win_team_mvp":"ぱぱ"},{"win_team_name":"しゃけ","win_team_mvp":"ぱぱ"},{"win_team_name":"ツナマヨ","win_team_mvp":"イカたろう"},{"win_team_name":"ツナマヨ","win_team_mvp":"オガトゥーン"},{"win_team_name":"しゃけ","win_team_mvp":"KAEDE"},{"win_team_name":"しゃけ","win_team_mvp":"とりたぐい。"},{"win_team_name":"ツナマヨ","win_team_mvp":"はる"},{"win_team_name":"しゃけ","win_team_mvp":"A.iƒ"},{"win_team_name":"しゃけ","win_team_mvp":"ほりぃ"},{"win_team_name":"ツナマヨ","win_team_mvp":"ハカセ"},{"win_team_name":"しゃけ","win_team_mvp":"ほーちゃん"},{"win_team_name":"しゃけ","win_team_mvp":"MM"},{"win_team_name":"ツナマヨ","win_team_mvp":"pokoppe♪"},{"win_team_name":"しゃけ","win_team_mvp":"あんな"},{"win_team_name":"しゃけ","win_team_mvp":"ひろし"},{"win_team_name":"ツナマヨ","win_team_mvp":"☆ミータン☆"}]