[{"win_team_name":"コスプレ","win_team_mvp":"ほのおのせんし"},{"win_team_name":"オシャレ","win_team_mvp":"つかさ"},{"win_team_name":"オシャレ","win_team_mvp":"SJH.んー"},{"win_team_name":"オシャレ","win_team_mvp":"BLACK"},{"win_team_name":"オシャレ","win_team_mvp":"KEITA"},{"win_team_name":"コスプレ","win_team_mvp":"TANーFU"},{"win_team_name":"オシャレ","win_team_mvp":"500にゃんもふもふ"},{"win_team_name":"オシャレ","win_team_mvp":"た"},{"win_team_name":"コスプレ","win_team_mvp":"アナスタシア"},{"win_team_name":"オシャレ","win_team_mvp":"かなえ"},{"win_team_name":"オシャレ","win_team_mvp":"えったん"},{"win_team_name":"オシャレ","win_team_mvp":"ちんた"},{"win_team_name":"コスプレ","win_team_mvp":"あっちゃん"},{"win_team_name":"オシャレ","win_team_mvp":"　"},{"win_team_name":"オシャレ","win_team_mvp":"じゅり"},{"win_team_name":"オシャレ","win_team_mvp":"やいと"},{"win_team_name":"コスプレ","win_team_mvp":"フェルー"},{"win_team_name":"オシャレ","win_team_mvp":"たいせい"},{"win_team_name":"コスプレ","win_team_mvp":"しゅうと"},{"win_team_name":"コスプレ","win_team_mvp":"60、"},{"win_team_name":"オシャレ","win_team_mvp":"きろり"},{"win_team_name":"オシャレ","win_team_mvp":"ふろんてぃあ。"},{"win_team_name":"オシャレ","win_team_mvp":"Dan~"},{"win_team_name":"オシャレ","win_team_mvp":"ローブ"},{"win_team_name":"コスプレ","win_team_mvp":"たくま"},{"win_team_name":"オシャレ","win_team_mvp":"ホロ"},{"win_team_name":"コスプレ","win_team_mvp":"tEikyo"},{"win_team_name":"コスプレ","win_team_mvp":"ゆうま"},{"win_team_name":"コスプレ","win_team_mvp":"　　　れんぬん　　　"},{"win_team_name":"オシャレ","win_team_mvp":"おはぎ_ISN"},{"win_team_name":"コスプレ","win_team_mvp":"ryo"},{"win_team_name":"コスプレ","win_team_mvp":"やなぎ"},{"win_team_name":"オシャレ","win_team_mvp":"BB-8"},{"win_team_name":"オシャレ","win_team_mvp":"ゆー"},{"win_team_name":"コスプレ","win_team_mvp":"ただのタコ"},{"win_team_name":"コスプレ","win_team_mvp":"パルパル"},{"win_team_name":"コスプレ","win_team_mvp":"かづき"},{"win_team_name":"オシャレ","win_team_mvp":"メラゾロス"},{"win_team_name":"コスプレ","win_team_mvp":"たける"},{"win_team_name":"コスプレ","win_team_mvp":"アーマ"},{"win_team_name":"オシャレ","win_team_mvp":"はやと"},{"win_team_name":"オシャレ","win_team_mvp":"エンタ"},{"win_team_name":"オシャレ","win_team_mvp":"はるか"},{"win_team_name":"オシャレ","win_team_mvp":"イカ　　オニ"},{"win_team_name":"オシャレ","win_team_mvp":"ゆうたろう"},{"win_team_name":"オシャレ","win_team_mvp":"あっぷる"},{"win_team_name":"オシャレ","win_team_mvp":"*かなっち*"},{"win_team_name":"コスプレ","win_team_mvp":"あくま\u0026あくま"},{"win_team_name":"コスプレ","win_team_mvp":"しゅうすけ"},{"win_team_name":"オシャレ","win_team_mvp":"おとう"},{"win_team_name":"オシャレ","win_team_mvp":"いかさし"},{"win_team_name":"オシャレ","win_team_mvp":"しゅうと"},{"win_team_name":"コスプレ","win_team_mvp":"みさ"},{"win_team_name":"オシャレ","win_team_mvp":"あきすての"},{"win_team_name":"オシャレ","win_team_mvp":"ハル"},{"win_team_name":"オシャレ","win_team_mvp":"アーサー(モンスト)"},{"win_team_name":"コスプレ","win_team_mvp":"かいちいぬち"},{"win_team_name":"オシャレ","win_team_mvp":"モノクロ"},{"win_team_name":"オシャレ","win_team_mvp":"イカしてる?"},{"win_team_name":"オシャレ","win_team_mvp":"MARU"},{"win_team_name":"オシャレ","win_team_mvp":"こんぶ　のムニエル"},{"win_team_name":"オシャレ","win_team_mvp":"りくけん"},{"win_team_name":"オシャレ","win_team_mvp":"はるか"},{"win_team_name":"オシャレ","win_team_mvp":"Ch*けみかる"},{"win_team_name":"オシャレ","win_team_mvp":"じゅんた"},{"win_team_name":"コスプレ","win_team_mvp":"るいくん"},{"win_team_name":"オシャレ","win_team_mvp":"ゲゲゲのきたろうZ"},{"win_team_name":"オシャレ","win_team_mvp":"てんねんなこども"},{"win_team_name":"コスプレ","win_team_mvp":"じょにき"},{"win_team_name":"オシャレ","win_team_mvp":"ヒロ"},{"win_team_name":"オシャレ","win_team_mvp":"くおん"},{"win_team_name":"コスプレ","win_team_mvp":"らまは~。"},{"win_team_name":"オシャレ","win_team_mvp":"やまてんぐ"},{"win_team_name":"コスプレ","win_team_mvp":"せんぱんまん"},{"win_team_name":"コスプレ","win_team_mvp":"pop"},{"win_team_name":"オシャレ","win_team_mvp":"けいし"},{"win_team_name":"コスプレ","win_team_mvp":"atipo"},{"win_team_name":"コスプレ","win_team_mvp":"アノマロカリス"},{"win_team_name":"コスプレ","win_team_mvp":"かくれスナイパー"},{"win_team_name":"オシャレ","win_team_mvp":"†イクラ†"},{"win_team_name":"コスプレ","win_team_mvp":"ゆうと"},{"win_team_name":"コスプレ","win_team_mvp":"ビビ"},{"win_team_name":"オシャレ","win_team_mvp":"REMジョニーKMF"},{"win_team_name":"コスプレ","win_team_mvp":"かいと"},{"win_team_name":"コスプレ","win_team_mvp":"Ch*たちゅοωο♂"},{"win_team_name":"オシャレ","win_team_mvp":"はるき"},{"win_team_name":"オシャレ","win_team_mvp":"RFC_たいやき"},{"win_team_name":"コスプレ","win_team_mvp":"ς('ώ'ゆ)ゝば"},{"win_team_name":"オシャレ","win_team_mvp":"おこた"},{"win_team_name":"オシャレ","win_team_mvp":"なみへぇ～。"},{"win_team_name":"コスプレ","win_team_mvp":"ENJ∴なつみ"},{"win_team_name":"オシャレ","win_team_mvp":"あーちゃん"},{"win_team_name":"コスプレ","win_team_mvp":"ふぉるて"},{"win_team_name":"オシャレ","win_team_mvp":"ぽぽひめ(∀)☆"},{"win_team_name":"オシャレ","win_team_mvp":"こぐら"},{"win_team_name":"オシャレ","win_team_mvp":"おうすけ"},{"win_team_name":"コスプレ","win_team_mvp":"くそざこナメクジいふ"},{"win_team_name":"オシャレ","win_team_mvp":"トラ"},{"win_team_name":"コスプレ","win_team_mvp":"1up.しいたけ"},{"win_team_name":"コスプレ","win_team_mvp":"ゆうきょうだい"},{"win_team_name":"オシャレ","win_team_mvp":"はなよドラゴン♪"}]