[{"win_team_name":"コスプレ","win_team_mvp":"★レイハル★"},{"win_team_name":"オシャレ","win_team_mvp":"Min.G もりぃ"},{"win_team_name":"オシャレ","win_team_mvp":"はるか"},{"win_team_name":"オシャレ","win_team_mvp":"めぐたん"},{"win_team_name":"コスプレ","win_team_mvp":"たくみーマン"},{"win_team_name":"オシャレ","win_team_mvp":"ユッケ"},{"win_team_name":"コスプレ","win_team_mvp":"ぱんつ"},{"win_team_name":"コスプレ","win_team_mvp":"ガロウ"},{"win_team_name":"オシャレ","win_team_mvp":"うっくん"},{"win_team_name":"コスプレ","win_team_mvp":"エミーちゃん"},{"win_team_name":"コスプレ","win_team_mvp":"ナイスするイカ2ごう"},{"win_team_name":"オシャレ","win_team_mvp":"あらし"},{"win_team_name":"オシャレ","win_team_mvp":"みゆ"},{"win_team_name":"オシャレ","win_team_mvp":"めけめけ#YMBL"},{"win_team_name":"コスプレ","win_team_mvp":"せいや"},{"win_team_name":"コスプレ","win_team_mvp":"やすお"},{"win_team_name":"オシャレ","win_team_mvp":"Gastrodon"},{"win_team_name":"オシャレ","win_team_mvp":"ネム"},{"win_team_name":"コスプレ","win_team_mvp":"BOO YAH!"},{"win_team_name":"オシャレ","win_team_mvp":"いおり"},{"win_team_name":"オシャレ","win_team_mvp":"ゴリラトゥーン"},{"win_team_name":"コスプレ","win_team_mvp":"けんちき"},{"win_team_name":"オシャレ","win_team_mvp":"ひとみ"},{"win_team_name":"コスプレ","win_team_mvp":"ピーチ*タイガ"},{"win_team_name":"コスプレ","win_team_mvp":"ふぇん"},{"win_team_name":"コスプレ","win_team_mvp":"ごはんのとも"},{"win_team_name":"オシャレ","win_team_mvp":"かると"},{"win_team_name":"コスプレ","win_team_mvp":"なごみ"},{"win_team_name":"コスプレ","win_team_mvp":"イリア"},{"win_team_name":"オシャレ","win_team_mvp":"チョコッシー"},{"win_team_name":"オシャレ","win_team_mvp":"たけし"},{"win_team_name":"コスプレ","win_team_mvp":"しみあき"},{"win_team_name":"コスプレ","win_team_mvp":"tomato"},{"win_team_name":"コスプレ","win_team_mvp":"にゃんちゅう"},{"win_team_name":"コスプレ","win_team_mvp":"ふく"},{"win_team_name":"オシャレ","win_team_mvp":"まんめんみ"},{"win_team_name":"オシャレ","win_team_mvp":"nyomu"},{"win_team_name":"オシャレ","win_team_mvp":"UNC_♪ひくらげ♪"},{"win_team_name":"オシャレ","win_team_mvp":"イオナ"},{"win_team_name":"コスプレ","win_team_mvp":"だいこんのあし"},{"win_team_name":"オシャレ","win_team_mvp":"きなこ"},{"win_team_name":"オシャレ","win_team_mvp":"さんご"},{"win_team_name":"オシャレ","win_team_mvp":"ミラー"},{"win_team_name":"オシャレ","win_team_mvp":"やぶりん!"},{"win_team_name":"コスプレ","win_team_mvp":"A4"},{"win_team_name":"コスプレ","win_team_mvp":"おみや"},{"win_team_name":"コスプレ","win_team_mvp":"†ıгeηeρα†"},{"win_team_name":"オシャレ","win_team_mvp":"カレーライス(∂∂)"},{"win_team_name":"コスプレ","win_team_mvp":"てーけ"},{"win_team_name":"オシャレ","win_team_mvp":"うみ"},{"win_team_name":"コスプレ","win_team_mvp":"げそこ"},{"win_team_name":"オシャレ","win_team_mvp":"はくと"},{"win_team_name":"オシャレ","win_team_mvp":"フレーバーですから♪"},{"win_team_name":"オシャレ","win_team_mvp":"ゆう"},{"win_team_name":"コスプレ","win_team_mvp":"アイラ"},{"win_team_name":"コスプレ","win_team_mvp":"とうふ"},{"win_team_name":"コスプレ","win_team_mvp":"しらいし"},{"win_team_name":"オシャレ","win_team_mvp":"みお"},{"win_team_name":"コスプレ","win_team_mvp":"ヒロヒロ"},{"win_team_name":"オシャレ","win_team_mvp":"S.M 8.1.9"},{"win_team_name":"オシャレ","win_team_mvp":"Rina"},{"win_team_name":"コスプレ","win_team_mvp":"あっくん"},{"win_team_name":"コスプレ","win_team_mvp":"こあくま"},{"win_team_name":"コスプレ","win_team_mvp":"イカなみのみぃさん"},{"win_team_name":"コスプレ","win_team_mvp":"ASA"},{"win_team_name":"オシャレ","win_team_mvp":"まめちゃん"},{"win_team_name":"コスプレ","win_team_mvp":"なっちゃん"},{"win_team_name":"オシャレ","win_team_mvp":"たちうお"},{"win_team_name":"コスプレ","win_team_mvp":"ちゅう"},{"win_team_name":"オシャレ","win_team_mvp":"ミラ"},{"win_team_name":"オシャレ","win_team_mvp":"なをわ"},{"win_team_name":"オシャレ","win_team_mvp":"ネッヂー"},{"win_team_name":"オシャレ","win_team_mvp":"おと"},{"win_team_name":"コスプレ","win_team_mvp":"つきしろ"},{"win_team_name":"オシャレ","win_team_mvp":"いもゴリラ"},{"win_team_name":"コスプレ","win_team_mvp":"Mr.マドンナちゃん"},{"win_team_name":"コスプレ","win_team_mvp":"インコメ"},{"win_team_name":"オシャレ","win_team_mvp":"やざわ"},{"win_team_name":"オシャレ","win_team_mvp":"なおりん"},{"win_team_name":"オシャレ","win_team_mvp":"ねぎだこキング1"},{"win_team_name":"オシャレ","win_team_mvp":"ぎんのエンゼル"},{"win_team_name":"オシャレ","win_team_mvp":"なーな"},{"win_team_name":"コスプレ","win_team_mvp":"Yakui"},{"win_team_name":"コスプレ","win_team_mvp":"カリッコリー"},{"win_team_name":"コスプレ","win_team_mvp":"HAHAHAHA!"},{"win_team_name":"コスプレ","win_team_mvp":"ツヨシーー"},{"win_team_name":"コスプレ","win_team_mvp":"みー"},{"win_team_name":"コスプレ","win_team_mvp":"じゅんや"},{"win_team_name":"コスプレ","win_team_mvp":"($_$)"},{"win_team_name":"コスプレ","win_team_mvp":"くうと"},{"win_team_name":"コスプレ","win_team_mvp":"Rion"},{"win_team_name":"コスプレ","win_team_mvp":"ヘタクソン"},{"win_team_name":"オシャレ","win_team_mvp":"しげはる"},{"win_team_name":"オシャレ","win_team_mvp":"Boo★コナン"},{"win_team_name":"コスプレ","win_team_mvp":"たかはしたかし"},{"win_team_name":"オシャレ","win_team_mvp":"きょんきょん"},{"win_team_name":"オシャレ","win_team_mvp":"サイト"},{"win_team_name":"コスプレ","win_team_mvp":"サーズ"},{"win_team_name":"コスプレ","win_team_mvp":"ねこりり"}]