[{"win_team_name":"だいじに","win_team_mvp":"☆KRT☆ダイキ☆"},{"win_team_name":"ガンガン","win_team_mvp":"とうふ"},{"win_team_name":"だいじに","win_team_mvp":"ゆう"},{"win_team_name":"ガンガン","win_team_mvp":"N.O.00"},{"win_team_name":"ガンガン","win_team_mvp":"Rafel"},{"win_team_name":"ガンガン","win_team_mvp":"すぷらすぴなー"},{"win_team_name":"だいじに","win_team_mvp":"いっさ"},{"win_team_name":"だいじに","win_team_mvp":"ヨーキー"},{"win_team_name":"ガンガン","win_team_mvp":"のろわれたイカ?"},{"win_team_name":"ガンガン","win_team_mvp":"さなっち"},{"win_team_name":"ガンガン","win_team_mvp":"だいふく"},{"win_team_name":"ガンガン","win_team_mvp":"POPO!"},{"win_team_name":"ガンガン","win_team_mvp":"しんちゃん"},{"win_team_name":"ガンガン","win_team_mvp":"あっくん"},{"win_team_name":"だいじに","win_team_mvp":"トシラトゥーン"},{"win_team_name":"ガンガン","win_team_mvp":"しんやとうさん"},{"win_team_name":"ガンガン","win_team_mvp":"こと"},{"win_team_name":"ガンガン","win_team_mvp":"りーく!"},{"win_team_name":"ガンガン","win_team_mvp":"イッキ"},{"win_team_name":"だいじに","win_team_mvp":"けにょーる"},{"win_team_name":"ガンガン","win_team_mvp":"あいぼ"},{"win_team_name":"ガンガン","win_team_mvp":"ヤイト"},{"win_team_name":"だいじに","win_team_mvp":"しょうよう"},{"win_team_name":"だいじに","win_team_mvp":"いちご*たると"},{"win_team_name":"だいじに","win_team_mvp":"*hiro*"},{"win_team_name":"ガンガン","win_team_mvp":"いかてんぷら"},{"win_team_name":"ガンガン","win_team_mvp":"プリッツ(^_^)"},{"win_team_name":"ガンガン","win_team_mvp":"スルメイカ"},{"win_team_name":"だいじに","win_team_mvp":"りょう"},{"win_team_name":"ガンガン","win_team_mvp":"イカすシューターズ1"},{"win_team_name":"だいじに","win_team_mvp":"ひろや"},{"win_team_name":"ガンガン","win_team_mvp":"しおん"},{"win_team_name":"ガンガン","win_team_mvp":"こっけいなピエロ"},{"win_team_name":"だいじに","win_team_mvp":"AMKT$ザーボン!"},{"win_team_name":"ガンガン","win_team_mvp":"トム\u0026ジェリー"},{"win_team_name":"ガンガン","win_team_mvp":"まさつゆちゃん"},{"win_team_name":"ガンガン","win_team_mvp":"フアイヤーホース"},{"win_team_name":"ガンガン","win_team_mvp":"まりお´"},{"win_team_name":"ガンガン","win_team_mvp":"ひか"},{"win_team_name":"ガンガン","win_team_mvp":"グウェンドリン"},{"win_team_name":"だいじに","win_team_mvp":"たける"},{"win_team_name":"ガンガン","win_team_mvp":"かいくん"},{"win_team_name":"だいじに","win_team_mvp":"いかぱか"},{"win_team_name":"だいじに","win_team_mvp":"さーちゃん"},{"win_team_name":"だいじに","win_team_mvp":"まっちゃん"},{"win_team_name":"だいじに","win_team_mvp":"Buzz★ "},{"win_team_name":"だいじに","win_team_mvp":"ピーマン、"},{"win_team_name":"だいじに","win_team_mvp":"ポールマッカートニー"},{"win_team_name":"だいじに","win_team_mvp":"ORANGE"},{"win_team_name":"だいじに","win_team_mvp":"トロサーモン"},{"win_team_name":"ガンガン","win_team_mvp":"ななほ"},{"win_team_name":"ガンガン","win_team_mvp":"ガンガンいこうぜ!"},{"win_team_name":"だいじに","win_team_mvp":"いろ"},{"win_team_name":"だいじに","win_team_mvp":"りっきー"},{"win_team_name":"だいじに","win_team_mvp":"なおた"},{"win_team_name":"ガンガン","win_team_mvp":"*かける*"},{"win_team_name":"ガンガン","win_team_mvp":"こうせい"},{"win_team_name":"ガンガン","win_team_mvp":"かず"},{"win_team_name":"ガンガン","win_team_mvp":"ピクミソ"},{"win_team_name":"だいじに","win_team_mvp":"まゆ"},{"win_team_name":"ガンガン","win_team_mvp":"ともき"},{"win_team_name":"だいじに","win_team_mvp":"まっちゃ"},{"win_team_name":"ガンガン","win_team_mvp":"ぴっぴ"},{"win_team_name":"ガンガン","win_team_mvp":"とらぱぱ"},{"win_team_name":"だいじに","win_team_mvp":"かのイカ"},{"win_team_name":"ガンガン","win_team_mvp":"さやリン"},{"win_team_name":"ガンガン","win_team_mvp":"さつっきー"},{"win_team_name":"だいじに","win_team_mvp":"ミレミアムファルコン"},{"win_team_name":"ガンガン","win_team_mvp":"U"},{"win_team_name":"ガンガン","win_team_mvp":"ハンター"},{"win_team_name":"ガンガン","win_team_mvp":"ゆめ"},{"win_team_name":"だいじに","win_team_mvp":"GVX##リク##"},{"win_team_name":"ガンガン","win_team_mvp":"かなと"},{"win_team_name":"だいじに","win_team_mvp":"うらけん"},{"win_team_name":"だいじに","win_team_mvp":"りーすけ"},{"win_team_name":"ガンガン","win_team_mvp":"りょ~さん"},{"win_team_name":"ガンガン","win_team_mvp":"ほのか"},{"win_team_name":"だいじに","win_team_mvp":"ハリーポたロウ"},{"win_team_name":"ガンガン","win_team_mvp":"のざ"},{"win_team_name":"ガンガン","win_team_mvp":"みそみそ!"},{"win_team_name":"ガンガン","win_team_mvp":"るな"},{"win_team_name":"ガンガン","win_team_mvp":"ふゆみ"},{"win_team_name":"ガンガン","win_team_mvp":"カナ"},{"win_team_name":"ガンガン","win_team_mvp":"たかちゃん"},{"win_team_name":"だいじに","win_team_mvp":"ロコ"},{"win_team_name":"ガンガン","win_team_mvp":"☆☆YUKITO★★"},{"win_team_name":"ガンガン","win_team_mvp":"©☆とおとん☆®"},{"win_team_name":"だいじに","win_team_mvp":"どくたー"},{"win_team_name":"だいじに","win_team_mvp":"そーま"},{"win_team_name":"ガンガン","win_team_mvp":"イカかわいい～"},{"win_team_name":"だいじに","win_team_mvp":"かりん"}]