[{"win_team_name":"おカネ","win_team_mvp":"イチロー"},{"win_team_name":"おカネ","win_team_mvp":"たかはし"},{"win_team_name":"愛","win_team_mvp":"りょうちゃん"},{"win_team_name":"おカネ","win_team_mvp":"アロマ"},{"win_team_name":"おカネ","win_team_mvp":"タイタ"},{"win_team_name":"おカネ","win_team_mvp":"Radec"},{"win_team_name":"愛","win_team_mvp":"エイ"},{"win_team_name":"愛","win_team_mvp":"しょっぴー"},{"win_team_name":"愛","win_team_mvp":"ちゃんゆい"},{"win_team_name":"おカネ","win_team_mvp":"N"},{"win_team_name":"愛","win_team_mvp":"うにいくらちゃん"},{"win_team_name":"愛","win_team_mvp":"スペシャルウィーク"},{"win_team_name":"愛","win_team_mvp":"DJYU"},{"win_team_name":"愛","win_team_mvp":"まっちゃばばろあ"},{"win_team_name":"愛","win_team_mvp":"おはこ"},{"win_team_name":"おカネ","win_team_mvp":"セイホー"},{"win_team_name":"おカネ","win_team_mvp":"さとしMKー2"},{"win_team_name":"おカネ","win_team_mvp":"きむら　ひろき"},{"win_team_name":"愛","win_team_mvp":"MAHOTO"},{"win_team_name":"愛","win_team_mvp":"まっつー"},{"win_team_name":"おカネ","win_team_mvp":"はいいろパイセン!!"},{"win_team_name":"愛","win_team_mvp":"たける"},{"win_team_name":"愛","win_team_mvp":"SWORD168"},{"win_team_name":"愛","win_team_mvp":"ちょこ"},{"win_team_name":"愛","win_team_mvp":"シアン"},{"win_team_name":"愛","win_team_mvp":"downey_032"},{"win_team_name":"おカネ","win_team_mvp":"そんちょ"},{"win_team_name":"おカネ","win_team_mvp":"ももた"},{"win_team_name":"おカネ","win_team_mvp":"〒ゆ"},{"win_team_name":"愛","win_team_mvp":"まなちょす"},{"win_team_name":"おカネ","win_team_mvp":"ラオ"},{"win_team_name":"おカネ","win_team_mvp":"いずも"},{"win_team_name":"愛","win_team_mvp":"～★ぴろ★～"},{"win_team_name":"おカネ","win_team_mvp":"L'i_ぴぴぴぴくと"},{"win_team_name":"おカネ","win_team_mvp":"のみルドン.KMS"},{"win_team_name":"おカネ","win_team_mvp":"き"},{"win_team_name":"おカネ","win_team_mvp":"яこたя"},{"win_team_name":"おカネ","win_team_mvp":"りさまるちゃん"},{"win_team_name":"おカネ","win_team_mvp":"ギタンマムル"},{"win_team_name":"愛","win_team_mvp":"ハンター1ごうき"},{"win_team_name":"おカネ","win_team_mvp":"なてこくん∞OgNt"},{"win_team_name":"愛","win_team_mvp":"ゆうき"},{"win_team_name":"愛","win_team_mvp":"ニッシー"},{"win_team_name":"愛","win_team_mvp":"tomo⌒☆\""},{"win_team_name":"愛","win_team_mvp":"ユニラテ/のげんり"},{"win_team_name":"愛","win_team_mvp":"あか"},{"win_team_name":"おカネ","win_team_mvp":"£·G☆えあぽんぷ "},{"win_team_name":"おカネ","win_team_mvp":"tmtd"},{"win_team_name":"愛","win_team_mvp":"つだぁー"},{"win_team_name":"おカネ","win_team_mvp":"いがいが"},{"win_team_name":"おカネ","win_team_mvp":"しま"},{"win_team_name":"おカネ","win_team_mvp":"wisp"},{"win_team_name":"おカネ","win_team_mvp":"なお"},{"win_team_name":"おカネ","win_team_mvp":"きよと"},{"win_team_name":"おカネ","win_team_mvp":"いのちのおんじん"},{"win_team_name":"おカネ","win_team_mvp":"きょんこ"},{"win_team_name":"愛","win_team_mvp":"イグゼルド"},{"win_team_name":"おカネ","win_team_mvp":"うさうさ"},{"win_team_name":"おカネ","win_team_mvp":"ほだくん"},{"win_team_name":"おカネ","win_team_mvp":"かまこー"},{"win_team_name":"愛","win_team_mvp":"キョン"},{"win_team_name":"おカネ","win_team_mvp":"イロハ"},{"win_team_name":"愛","win_team_mvp":"ひとし"},{"win_team_name":"おカネ","win_team_mvp":"ドラねこ"},{"win_team_name":"おカネ","win_team_mvp":"ぬこぬこ"},{"win_team_name":"愛","win_team_mvp":"はやお"},{"win_team_name":"愛","win_team_mvp":"はる"},{"win_team_name":"おカネ","win_team_mvp":"スカーフゴンベ"},{"win_team_name":"愛","win_team_mvp":"LEN"},{"win_team_name":"愛","win_team_mvp":"りょった"},{"win_team_name":"おカネ","win_team_mvp":"かっこー"},{"win_team_name":"愛","win_team_mvp":"しゅんくん"},{"win_team_name":"おカネ","win_team_mvp":"AYANO!"},{"win_team_name":"おカネ","win_team_mvp":"ゆうや"},{"win_team_name":"愛","win_team_mvp":"けーちゃん"},{"win_team_name":"愛","win_team_mvp":"けんちゃん"},{"win_team_name":"愛","win_team_mvp":"とみ"},{"win_team_name":"愛","win_team_mvp":"しろ"},{"win_team_name":"おカネ","win_team_mvp":"エイムリー"},{"win_team_name":"おカネ","win_team_mvp":"dual.drαw"},{"win_team_name":"おカネ","win_team_mvp":"C3ƒクレア◇LC"},{"win_team_name":"愛","win_team_mvp":"ゆい"},{"win_team_name":"愛","win_team_mvp":"†いちよう†"},{"win_team_name":"おカネ","win_team_mvp":"あまる"},{"win_team_name":"愛","win_team_mvp":"ゆづを"},{"win_team_name":"おカネ","win_team_mvp":"おきく"},{"win_team_name":"おカネ","win_team_mvp":"みーさん"},{"win_team_name":"おカネ","win_team_mvp":"えだまめ"},{"win_team_name":"おカネ","win_team_mvp":"にたまごまるひろ"},{"win_team_name":"愛","win_team_mvp":"CRAN"},{"win_team_name":"愛","win_team_mvp":"rafin"},{"win_team_name":"おカネ","win_team_mvp":"ぴあーち#♂"}]