[{"win_team_name":"カンペキ頭脳","win_team_mvp":"りゅうと"},{"win_team_name":"カンペキ頭脳","win_team_mvp":"ノコがみ"},{"win_team_name":"カンペキ頭脳","win_team_mvp":"はし"},{"win_team_name":"カンペキカラダ","win_team_mvp":"terumin★MG"},{"win_team_name":"カンペキ頭脳","win_team_mvp":"T4_しん"},{"win_team_name":"カンペキカラダ","win_team_mvp":"まなみ"},{"win_team_name":"カンペキ頭脳","win_team_mvp":"ほずみ"},{"win_team_name":"カンペキカラダ","win_team_mvp":"ゼンマイ"},{"win_team_name":"カンペキカラダ","win_team_mvp":"たっちゃん"},{"win_team_name":"カンペキカラダ","win_team_mvp":"YSI"},{"win_team_name":"カンペキカラダ","win_team_mvp":"エイルス"},{"win_team_name":"カンペキ頭脳","win_team_mvp":"βMuruƒ⌒∀⌒„"},{"win_team_name":"カンペキ頭脳","win_team_mvp":"にせめん"},{"win_team_name":"カンペキカラダ","win_team_mvp":"パパのこいびと"},{"win_team_name":"カンペキ頭脳","win_team_mvp":"チシャミ"},{"win_team_name":"カンペキ頭脳","win_team_mvp":"tukumo"},{"win_team_name":"カンペキ頭脳","win_team_mvp":"ズキュゥウウウン"},{"win_team_name":"カンペキカラダ","win_team_mvp":"HIKARU"},{"win_team_name":"カンペキ頭脳","win_team_mvp":"たまねぎ"},{"win_team_name":"カンペキ頭脳","win_team_mvp":"ふーか"},{"win_team_name":"カンペキ頭脳","win_team_mvp":"みゃー"},{"win_team_name":"カンペキ頭脳","win_team_mvp":"　マーズ・ユエリア　"},{"win_team_name":"カンペキカラダ","win_team_mvp":"のう"},{"win_team_name":"カンペキカラダ","win_team_mvp":"S.R.D."},{"win_team_name":"カンペキ頭脳","win_team_mvp":"みさわ-TPG02"},{"win_team_name":"カンペキ頭脳","win_team_mvp":"きくたん"},{"win_team_name":"カンペキ頭脳","win_team_mvp":"りきゅう"},{"win_team_name":"カンペキ頭脳","win_team_mvp":"Euphe"},{"win_team_name":"カンペキカラダ","win_team_mvp":"トーマスサブチリス"},{"win_team_name":"カンペキ頭脳","win_team_mvp":"ウラトラナイマン"},{"win_team_name":"カンペキ頭脳","win_team_mvp":"しりでやってます"},{"win_team_name":"カンペキ頭脳","win_team_mvp":"はるお"},{"win_team_name":"カンペキカラダ","win_team_mvp":"みゅう"},{"win_team_name":"カンペキカラダ","win_team_mvp":"みゆき"},{"win_team_name":"カンペキ頭脳","win_team_mvp":"へいわしゆぎ01"},{"win_team_name":"カンペキカラダ","win_team_mvp":"りゅう"},{"win_team_name":"カンペキ頭脳","win_team_mvp":"うさぎ"},{"win_team_name":"カンペキ頭脳","win_team_mvp":"URA"},{"win_team_name":"カンペキカラダ","win_team_mvp":"ゆっきー"},{"win_team_name":"カンペキ頭脳","win_team_mvp":"テケトコ(+~+)/"},{"win_team_name":"カンペキカラダ","win_team_mvp":"ともき_TOMOKI"},{"win_team_name":"カンペキ頭脳","win_team_mvp":"にぶる"},{"win_team_name":"カンペキ頭脳","win_team_mvp":"T.N"},{"win_team_name":"カンペキ頭脳","win_team_mvp":"ぺはん/YMP"},{"win_team_name":"カンペキカラダ","win_team_mvp":"こしあん"},{"win_team_name":"カンペキカラダ","win_team_mvp":"JOKER"},{"win_team_name":"カンペキカラダ","win_team_mvp":"わだいこ"},{"win_team_name":"カンペキカラダ","win_team_mvp":"クロロ"},{"win_team_name":"カンペキカラダ","win_team_mvp":"ちか"},{"win_team_name":"カンペキ頭脳","win_team_mvp":"もつを"},{"win_team_name":"カンペキ頭脳","win_team_mvp":"ころすとのろわれるよ"},{"win_team_name":"カンペキ頭脳","win_team_mvp":"とむ"},{"win_team_name":"カンペキカラダ","win_team_mvp":"えりちゃん☆"},{"win_team_name":"カンペキカラダ","win_team_mvp":"たか"},{"win_team_name":"カンペキ頭脳","win_team_mvp":"ぽんこつらーめん"},{"win_team_name":"カンペキ頭脳","win_team_mvp":"たつまき"},{"win_team_name":"カンペキ頭脳","win_team_mvp":"ピノキオ"},{"win_team_name":"カンペキカラダ","win_team_mvp":"じょうたろう"},{"win_team_name":"カンペキ頭脳","win_team_mvp":".*りね*."},{"win_team_name":"カンペキカラダ","win_team_mvp":"こりぐーのぬし。イヌ"},{"win_team_name":"カンペキカラダ","win_team_mvp":"キングカズマ"},{"win_team_name":"カンペキカラダ","win_team_mvp":"チビ"},{"win_team_name":"カンペキカラダ","win_team_mvp":"ろうそく/fy"},{"win_team_name":"カンペキカラダ","win_team_mvp":"ちょくとれない\u003e\u003c"},{"win_team_name":"カンペキ頭脳","win_team_mvp":"しゅんた"},{"win_team_name":"カンペキカラダ","win_team_mvp":"あぱお(あばお)"},{"win_team_name":"カンペキ頭脳","win_team_mvp":"かのえにゃん"},{"win_team_name":"カンペキカラダ","win_team_mvp":"あーちゃん§Cruz"},{"win_team_name":"カンペキ頭脳","win_team_mvp":"gorozona"},{"win_team_name":"カンペキ頭脳","win_team_mvp":"ぴょんきち"},{"win_team_name":"カンペキ頭脳","win_team_mvp":"Hello"},{"win_team_name":"カンペキ頭脳","win_team_mvp":"デストマト"},{"win_team_name":"カンペキカラダ","win_team_mvp":"ANZU"},{"win_team_name":"カンペキ頭脳","win_team_mvp":"きょういちろう"},{"win_team_name":"カンペキカラダ","win_team_mvp":"フフフ・・・"},{"win_team_name":"カンペキカラダ","win_team_mvp":"ミサッピ"},{"win_team_name":"カンペキカラダ","win_team_mvp":"うさぎまる"},{"win_team_name":"カンペキ頭脳","win_team_mvp":"まつだ"},{"win_team_name":"カンペキカラダ","win_team_mvp":"メイサイ"},{"win_team_name":"カンペキ頭脳","win_team_mvp":"リン"},{"win_team_name":"カンペキカラダ","win_team_mvp":"ごじゃるん"},{"win_team_name":"カンペキカラダ","win_team_mvp":"33-4"},{"win_team_name":"カンペキカラダ","win_team_mvp":"ボ~イ"},{"win_team_name":"カンペキカラダ","win_team_mvp":"DFM"},{"win_team_name":"カンペキ頭脳","win_team_mvp":"とも"},{"win_team_name":"カンペキカラダ","win_team_mvp":"わかばーん☆"},{"win_team_name":"カンペキ頭脳","win_team_mvp":"チャン?"},{"win_team_name":"カンペキカラダ","win_team_mvp":"つくね"},{"win_team_name":"カンペキカラダ","win_team_mvp":"れいや"},{"win_team_name":"カンペキカラダ","win_team_mvp":"ゆう　く:コ€"},{"win_team_name":"カンペキ頭脳","win_team_mvp":"るぅあ★"}]