[{"win_team_name":"カンペキカラダ","win_team_mvp":"マエストロ"},{"win_team_name":"カンペキカラダ","win_team_mvp":"dosanko"},{"win_team_name":"カンペキカラダ","win_team_mvp":"ささっと"},{"win_team_name":"カンペキ頭脳","win_team_mvp":"ズヅ"},{"win_team_name":"カンペキカラダ","win_team_mvp":"ヤーユ"},{"win_team_name":"カンペキカラダ","win_team_mvp":"ほるもん"},{"win_team_name":"カンペキ頭脳","win_team_mvp":"もぐもぐ"},{"win_team_name":"カンペキ頭脳","win_team_mvp":"Fin_Merle"},{"win_team_name":"カンペキカラダ","win_team_mvp":"ƒSKƒ イカ"},{"win_team_name":"カンペキカラダ","win_team_mvp":"いれたてのコーヒー"},{"win_team_name":"カンペキ頭脳","win_team_mvp":"SOS★kkr"},{"win_team_name":"カンペキカラダ","win_team_mvp":"おとさん"},{"win_team_name":"カンペキカラダ","win_team_mvp":"masayan!"},{"win_team_name":"カンペキカラダ","win_team_mvp":"はると"},{"win_team_name":"カンペキカラダ","win_team_mvp":"とも"},{"win_team_name":"カンペキカラダ","win_team_mvp":"でんこ"},{"win_team_name":"カンペキカラダ","win_team_mvp":"さむ"},{"win_team_name":"カンペキカラダ","win_team_mvp":"みそラーメン"},{"win_team_name":"カンペキカラダ","win_team_mvp":"やそしむ"},{"win_team_name":"カンペキカラダ","win_team_mvp":"ぺれすとろイカ"},{"win_team_name":"カンペキカラダ","win_team_mvp":"Koji"},{"win_team_name":"カンペキ頭脳","win_team_mvp":"う\"ぁれん"},{"win_team_name":"カンペキカラダ","win_team_mvp":"rey"},{"win_team_name":"カンペキ頭脳","win_team_mvp":"どるやん"},{"win_team_name":"カンペキカラダ","win_team_mvp":"テツキレ"},{"win_team_name":"カンペキ頭脳","win_team_mvp":"にょぶ*たいし"},{"win_team_name":"カンペキカラダ","win_team_mvp":"むーさんたまりあ"},{"win_team_name":"カンペキカラダ","win_team_mvp":"ピーチッチ"},{"win_team_name":"カンペキカラダ","win_team_mvp":"うれー"},{"win_team_name":"カンペキ頭脳","win_team_mvp":"すいすい"},{"win_team_name":"カンペキカラダ","win_team_mvp":"オハマ"},{"win_team_name":"カンペキ頭脳","win_team_mvp":"ナカナカ"},{"win_team_name":"カンペキ頭脳","win_team_mvp":"ジャムをじさん"},{"win_team_name":"カンペキカラダ","win_team_mvp":"イリヤ"},{"win_team_name":"カンペキカラダ","win_team_mvp":"くろかびィイェアアァ"},{"win_team_name":"カンペキカラダ","win_team_mvp":"ビーコンみんなのもの"},{"win_team_name":"カンペキ頭脳","win_team_mvp":"たけがさつ(・д・)"},{"win_team_name":"カンペキ頭脳","win_team_mvp":"まつすけ"},{"win_team_name":"カンペキ頭脳","win_team_mvp":"キクウクタ"},{"win_team_name":"カンペキカラダ","win_team_mvp":"おれたピペット"},{"win_team_name":"カンペキ頭脳","win_team_mvp":"とくだい"},{"win_team_name":"カンペキ頭脳","win_team_mvp":"なぞのてんが3つ"},{"win_team_name":"カンペキ頭脳","win_team_mvp":"☆かみ☆"},{"win_team_name":"カンペキ頭脳","win_team_mvp":"ことり"},{"win_team_name":"カンペキ頭脳","win_team_mvp":"レジェンドクラフ"},{"win_team_name":"カンペキ頭脳","win_team_mvp":"べじた"},{"win_team_name":"カンペキカラダ","win_team_mvp":"よしきー"},{"win_team_name":"カンペキカラダ","win_team_mvp":"アラレんぼうしょぐん"},{"win_team_name":"カンペキカラダ","win_team_mvp":"みさき"},{"win_team_name":"カンペキ頭脳","win_team_mvp":"とらさん"},{"win_team_name":"カンペキカラダ","win_team_mvp":"マフィアのしたっぱ"},{"win_team_name":"カンペキ頭脳","win_team_mvp":"すてみムクホーク"},{"win_team_name":"カンペキカラダ","win_team_mvp":"カボ"},{"win_team_name":"カンペキカラダ","win_team_mvp":"りん"},{"win_team_name":"カンペキ頭脳","win_team_mvp":"けーた"},{"win_team_name":"カンペキカラダ","win_team_mvp":"маув*タブンネ"},{"win_team_name":"カンペキ頭脳","win_team_mvp":"せうきち#"},{"win_team_name":"カンペキ頭脳","win_team_mvp":"ふじはち"},{"win_team_name":"カンペキ頭脳","win_team_mvp":"たこのするめちん"},{"win_team_name":"カンペキカラダ","win_team_mvp":"マーチ"},{"win_team_name":"カンペキ頭脳","win_team_mvp":"ここでセーブするか?"},{"win_team_name":"カンペキカラダ","win_team_mvp":"おに"},{"win_team_name":"カンペキカラダ","win_team_mvp":"AKIRA"},{"win_team_name":"カンペキカラダ","win_team_mvp":"ぐうのネ.MoB"},{"win_team_name":"カンペキカラダ","win_team_mvp":"しゅり"},{"win_team_name":"カンペキ頭脳","win_team_mvp":"もち"},{"win_team_name":"カンペキ頭脳","win_team_mvp":"ギブド"},{"win_team_name":"カンペキカラダ","win_team_mvp":"みじんこ"},{"win_team_name":"カンペキ頭脳","win_team_mvp":"おりがみみこと#LV"},{"win_team_name":"カンペキ頭脳","win_team_mvp":"ラノ"},{"win_team_name":"カンペキカラダ","win_team_mvp":"◆しきなん。"},{"win_team_name":"カンペキカラダ","win_team_mvp":"nice"},{"win_team_name":"カンペキ頭脳","win_team_mvp":"じゅけんせい"},{"win_team_name":"カンペキ頭脳","win_team_mvp":"t3"},{"win_team_name":"カンペキカラダ","win_team_mvp":"みゃん"},{"win_team_name":"カンペキカラダ","win_team_mvp":"caτ♪*らいむ*♭"},{"win_team_name":"カンペキカラダ","win_team_mvp":"ちくわ"},{"win_team_name":"カンペキカラダ","win_team_mvp":"こん#マスカット"},{"win_team_name":"カンペキ頭脳","win_team_mvp":"さよ"},{"win_team_name":"カンペキカラダ","win_team_mvp":"まかだみあなっつ"},{"win_team_name":"カンペキカラダ","win_team_mvp":"NOAH"},{"win_team_name":"カンペキカラダ","win_team_mvp":"なっとうねばねば。"},{"win_team_name":"カンペキカラダ","win_team_mvp":"ちとせあめ"},{"win_team_name":"カンペキカラダ","win_team_mvp":"3Kれんしゅー"},{"win_team_name":"カンペキカラダ","win_team_mvp":"うず"},{"win_team_name":"カンペキ頭脳","win_team_mvp":"プッカれもんあじスキ"},{"win_team_name":"カンペキカラダ","win_team_mvp":"フレンドとうろくよろ"},{"win_team_name":"カンペキ頭脳","win_team_mvp":"Arsyu*EMP"},{"win_team_name":"カンペキカラダ","win_team_mvp":"まつの　チョロまつ"},{"win_team_name":"カンペキ頭脳","win_team_mvp":"tkm"},{"win_team_name":"カンペキ頭脳","win_team_mvp":"*ぜつぼうのなみだ*"}]