[{"win_team_name":"グリーン","win_team_mvp":"ぱぱ"},{"win_team_name":"レッド","win_team_mvp":"れんくん"},{"win_team_name":"グリーン","win_team_mvp":"ボンジュール!"},{"win_team_name":"グリーン","win_team_mvp":"いかむすめ ϋ"},{"win_team_name":"レッド","win_team_mvp":"Nobu123"},{"win_team_name":"グリーン","win_team_mvp":"ちかアイドル"},{"win_team_name":"レッド","win_team_mvp":"ロキ"},{"win_team_name":"グリーン","win_team_mvp":"ギガ"},{"win_team_name":"グリーン","win_team_mvp":"はなにつめたポテチ"},{"win_team_name":"グリーン","win_team_mvp":"Qoo"},{"win_team_name":"グリーン","win_team_mvp":"TOMO73"},{"win_team_name":"グリーン","win_team_mvp":"anm"},{"win_team_name":"グリーン","win_team_mvp":"ぽよ"},{"win_team_name":"グリーン","win_team_mvp":"うさぎ.MIS"},{"win_team_name":"レッド","win_team_mvp":"かなべる"},{"win_team_name":"レッド","win_team_mvp":"ふくちゃん"},{"win_team_name":"グリーン","win_team_mvp":"わっしょいおじさん"},{"win_team_name":"レッド","win_team_mvp":"Gallia"},{"win_team_name":"グリーン","win_team_mvp":"MAH.Miyaak"},{"win_team_name":"レッド","win_team_mvp":"みあ"},{"win_team_name":"グリーン","win_team_mvp":"こうちゃん"},{"win_team_name":"グリーン","win_team_mvp":"ワンスター-0413"},{"win_team_name":"グリーン","win_team_mvp":"BKT_オカ"},{"win_team_name":"レッド","win_team_mvp":"さぬきudon"},{"win_team_name":"レッド","win_team_mvp":"すずぽこ"},{"win_team_name":"レッド","win_team_mvp":"へごちょ"},{"win_team_name":"レッド","win_team_mvp":"riku"},{"win_team_name":"グリーン","win_team_mvp":"ナシ"},{"win_team_name":"グリーン","win_team_mvp":"ばんじー"},{"win_team_name":"レッド","win_team_mvp":"まかろん"},{"win_team_name":"グリーン","win_team_mvp":"おゆ"},{"win_team_name":"グリーン","win_team_mvp":"わっと"},{"win_team_name":"グリーン","win_team_mvp":"ダーパ"},{"win_team_name":"レッド","win_team_mvp":"タク"},{"win_team_name":"グリーン","win_team_mvp":"りんくす"},{"win_team_name":"レッド","win_team_mvp":"スナイパーさいごう"},{"win_team_name":"グリーン","win_team_mvp":"えりな"},{"win_team_name":"レッド","win_team_mvp":"てぃらみす"},{"win_team_name":"レッド","win_team_mvp":"おだっち"},{"win_team_name":"グリーン","win_team_mvp":"さの"},{"win_team_name":"グリーン","win_team_mvp":"いも"},{"win_team_name":"グリーン","win_team_mvp":"メスト"},{"win_team_name":"グリーン","win_team_mvp":"ヨウ"},{"win_team_name":"グリーン","win_team_mvp":"そげキング"},{"win_team_name":"グリーン","win_team_mvp":"わんぱくボーイ"},{"win_team_name":"グリーン","win_team_mvp":"ひでゆき"},{"win_team_name":"レッド","win_team_mvp":"R.S"},{"win_team_name":"グリーン","win_team_mvp":"C.マッケンジー"},{"win_team_name":"グリーン","win_team_mvp":"にゃろ"},{"win_team_name":"グリーン","win_team_mvp":"くーさん"},{"win_team_name":"レッド","win_team_mvp":"みさき"},{"win_team_name":"レッド","win_team_mvp":"うしろいるのにざせき"},{"win_team_name":"グリーン","win_team_mvp":"がるお*るぅさん"},{"win_team_name":"レッド","win_team_mvp":"そうき"},{"win_team_name":"レッド","win_team_mvp":"KJ"},{"win_team_name":"レッド","win_team_mvp":"テメェー!まっさつ!"},{"win_team_name":"レッド","win_team_mvp":"※ダイオウグソクムシ"},{"win_team_name":"グリーン","win_team_mvp":"けー"},{"win_team_name":"グリーン","win_team_mvp":"あやと"},{"win_team_name":"レッド","win_team_mvp":"くきわかめ"},{"win_team_name":"レッド","win_team_mvp":"ヨッシーZEX"},{"win_team_name":"グリーン","win_team_mvp":"シアン"},{"win_team_name":"レッド","win_team_mvp":"しゅん"},{"win_team_name":"レッド","win_team_mvp":"たろう"},{"win_team_name":"レッド","win_team_mvp":"じーり"},{"win_team_name":"レッド","win_team_mvp":"くろゆきひめ"},{"win_team_name":"レッド","win_team_mvp":"たえちゃん"},{"win_team_name":"グリーン","win_team_mvp":"なな"},{"win_team_name":"レッド","win_team_mvp":"ユーすけ"},{"win_team_name":"グリーン","win_team_mvp":"Red"},{"win_team_name":"レッド","win_team_mvp":"しゅん SS"},{"win_team_name":"グリーン","win_team_mvp":"あんず"},{"win_team_name":"レッド","win_team_mvp":"UK"},{"win_team_name":"レッド","win_team_mvp":"シフォー"},{"win_team_name":"グリーン","win_team_mvp":"ひだり"},{"win_team_name":"レッド","win_team_mvp":"だいき"},{"win_team_name":"グリーン","win_team_mvp":"しらす"},{"win_team_name":"グリーン","win_team_mvp":"スクウィッド"},{"win_team_name":"レッド","win_team_mvp":"こよ"},{"win_team_name":"レッド","win_team_mvp":"ツユクサ"},{"win_team_name":"グリーン","win_team_mvp":"マサトゥーン"},{"win_team_name":"レッド","win_team_mvp":"ジル"},{"win_team_name":"グリーン","win_team_mvp":"きくま"},{"win_team_name":"グリーン","win_team_mvp":"あああ"},{"win_team_name":"グリーン","win_team_mvp":"まっちゃん"},{"win_team_name":"レッド","win_team_mvp":"ぽやんち"},{"win_team_name":"レッド","win_team_mvp":"KINいくみ"},{"win_team_name":"レッド","win_team_mvp":"りょう"},{"win_team_name":"レッド","win_team_mvp":"ink_いのまたし"},{"win_team_name":"グリーン","win_team_mvp":"maran*YUU"},{"win_team_name":"グリーン","win_team_mvp":"はるまき"}]