[{"win_team_name":"グリーン","win_team_mvp":"さーた"},{"win_team_name":"グリーン","win_team_mvp":"あんぜんバナナ"},{"win_team_name":"レッド","win_team_mvp":"ゆっくり★ひか"},{"win_team_name":"グリーン","win_team_mvp":"NOVITA"},{"win_team_name":"グリーン","win_team_mvp":"あやちゃん"},{"win_team_name":"レッド","win_team_mvp":"oyster"},{"win_team_name":"レッド","win_team_mvp":"バクタン"},{"win_team_name":"レッド","win_team_mvp":"ink*るい"},{"win_team_name":"レッド","win_team_mvp":"ふつふつ"},{"win_team_name":"グリーン","win_team_mvp":"Chronos"},{"win_team_name":"レッド","win_team_mvp":"ぞのみぃる"},{"win_team_name":"レッド","win_team_mvp":"さとし"},{"win_team_name":"グリーン","win_team_mvp":"ハンターイカ"},{"win_team_name":"レッド","win_team_mvp":"ベイマックス"},{"win_team_name":"レッド","win_team_mvp":"ドクガンリュウ"},{"win_team_name":"レッド","win_team_mvp":"$*\u0026#!"},{"win_team_name":"レッド","win_team_mvp":"しゅん"},{"win_team_name":"グリーン","win_team_mvp":"shaela"},{"win_team_name":"グリーン","win_team_mvp":"ゆかりけろ"},{"win_team_name":"グリーン","win_team_mvp":"ちいこ"},{"win_team_name":"グリーン","win_team_mvp":"はるい"},{"win_team_name":"グリーン","win_team_mvp":"シバfaシュri"},{"win_team_name":"グリーン","win_team_mvp":"min."},{"win_team_name":"レッド","win_team_mvp":"わきみず"},{"win_team_name":"グリーン","win_team_mvp":"キノセイ"},{"win_team_name":"レッド","win_team_mvp":"paisu"},{"win_team_name":"レッド","win_team_mvp":"こんたい"},{"win_team_name":"レッド","win_team_mvp":"☆Lucy☆"},{"win_team_name":"グリーン","win_team_mvp":"あさせでバチャバチャ"},{"win_team_name":"レッド","win_team_mvp":"ゆう"},{"win_team_name":"グリーン","win_team_mvp":"#あくるせん#"},{"win_team_name":"レッド","win_team_mvp":"てぃん"},{"win_team_name":"レッド","win_team_mvp":"ふーちゃん"},{"win_team_name":"グリーン","win_team_mvp":"りえっち"},{"win_team_name":"グリーン","win_team_mvp":"コイキング"},{"win_team_name":"レッド","win_team_mvp":"いぶき"},{"win_team_name":"レッド","win_team_mvp":"ラーメンみそあじくん"},{"win_team_name":"グリーン","win_team_mvp":"アルミニウム"},{"win_team_name":"グリーン","win_team_mvp":"ココ"},{"win_team_name":"グリーン","win_team_mvp":"KS/となりのトロロ"},{"win_team_name":"レッド","win_team_mvp":"チンチラマスター"},{"win_team_name":"レッド","win_team_mvp":"ちかちゃん"},{"win_team_name":"レッド","win_team_mvp":"ゆきうな"},{"win_team_name":"グリーン","win_team_mvp":"あおいずみ"},{"win_team_name":"グリーン","win_team_mvp":"かぷちぃの"},{"win_team_name":"レッド","win_team_mvp":"shiruku"},{"win_team_name":"グリーン","win_team_mvp":"らじあた.Regen"},{"win_team_name":"グリーン","win_team_mvp":"ywmex229VH"},{"win_team_name":"レッド","win_team_mvp":"まんめんまめみ"},{"win_team_name":"グリーン","win_team_mvp":"うちべんけい"},{"win_team_name":"グリーン","win_team_mvp":"TKG"},{"win_team_name":"グリーン","win_team_mvp":"DARS"},{"win_team_name":"レッド","win_team_mvp":"モスクワ"},{"win_team_name":"グリーン","win_team_mvp":"けろい"},{"win_team_name":"グリーン","win_team_mvp":"めたモん"},{"win_team_name":"レッド","win_team_mvp":"('`)"},{"win_team_name":"グリーン","win_team_mvp":"JESPER"},{"win_team_name":"レッド","win_team_mvp":"SK_◇りっくん◇"},{"win_team_name":"グリーン","win_team_mvp":"シェン-カー"},{"win_team_name":"グリーン","win_team_mvp":"よう"},{"win_team_name":"グリーン","win_team_mvp":"よっちゃん"},{"win_team_name":"グリーン","win_team_mvp":"かえるあじ　ももこ"},{"win_team_name":"グリーン","win_team_mvp":"ゆうた2"},{"win_team_name":"グリーン","win_team_mvp":"プチかいと"},{"win_team_name":"グリーン","win_team_mvp":"りんか"},{"win_team_name":"グリーン","win_team_mvp":"【daru】"},{"win_team_name":"レッド","win_team_mvp":"セルウィン"},{"win_team_name":"グリーン","win_team_mvp":"カズヤトゥーン"},{"win_team_name":"グリーン","win_team_mvp":"[IKSM]ゲックン"},{"win_team_name":"グリーン","win_team_mvp":"⊂(;∀;)⊃ブーン"},{"win_team_name":"レッド","win_team_mvp":"なるみ"},{"win_team_name":"グリーン","win_team_mvp":"☆☆Shouma☆☆"},{"win_team_name":"グリーン","win_team_mvp":"イカつれんー"},{"win_team_name":"グリーン","win_team_mvp":"きくつぎりゅうと"},{"win_team_name":"グリーン","win_team_mvp":"むしばこわいクラゲ"},{"win_team_name":"グリーン","win_team_mvp":"+_ちゃんぽん-+"},{"win_team_name":"グリーン","win_team_mvp":"ぎんさん"},{"win_team_name":"レッド","win_team_mvp":"えいちやん"},{"win_team_name":"レッド","win_team_mvp":"ひびき"},{"win_team_name":"グリーン","win_team_mvp":"maron"},{"win_team_name":"グリーン","win_team_mvp":"ともちん"},{"win_team_name":"グリーン","win_team_mvp":"kkr"},{"win_team_name":"グリーン","win_team_mvp":"おおとも"},{"win_team_name":"レッド","win_team_mvp":"につけ"},{"win_team_name":"グリーン","win_team_mvp":"*あぷりこっと*"},{"win_team_name":"グリーン","win_team_mvp":"アリカ"},{"win_team_name":"グリーン","win_team_mvp":"ひらい"},{"win_team_name":"レッド","win_team_mvp":"YuRina"},{"win_team_name":"グリーン","win_team_mvp":"ゆきねこ"},{"win_team_name":"レッド","win_team_mvp":"ゴッド"},{"win_team_name":"レッド","win_team_mvp":"なな"}]