[{"win_team_name":"グリーン","win_team_mvp":"むすむす"},{"win_team_name":"レッド","win_team_mvp":"なるこ"},{"win_team_name":"レッド","win_team_mvp":"ひびき"},{"win_team_name":"グリーン","win_team_mvp":"ゆや"},{"win_team_name":"レッド","win_team_mvp":"うめぼし"},{"win_team_name":"グリーン","win_team_mvp":"しおりん"},{"win_team_name":"グリーン","win_team_mvp":"Peltz"},{"win_team_name":"グリーン","win_team_mvp":"あらちょん"},{"win_team_name":"グリーン","win_team_mvp":"バースト・インカー"},{"win_team_name":"レッド","win_team_mvp":"しょうへい"},{"win_team_name":"レッド","win_team_mvp":"まなまな"},{"win_team_name":"レッド","win_team_mvp":"hayata"},{"win_team_name":"グリーン","win_team_mvp":"ふでおろしじぇいえす"},{"win_team_name":"レッド","win_team_mvp":"はやと"},{"win_team_name":"レッド","win_team_mvp":"アッキー"},{"win_team_name":"レッド","win_team_mvp":"けんとぅ"},{"win_team_name":"レッド","win_team_mvp":"まるこ_NKS"},{"win_team_name":"レッド","win_team_mvp":"クロム"},{"win_team_name":"レッド","win_team_mvp":"ひでんよういん"},{"win_team_name":"グリーン","win_team_mvp":"チャンタ"},{"win_team_name":"レッド","win_team_mvp":"ひとのこゆかり"},{"win_team_name":"レッド","win_team_mvp":"かずま kazuma"},{"win_team_name":"グリーン","win_team_mvp":"かあねん"},{"win_team_name":"レッド","win_team_mvp":"ふゆざくら"},{"win_team_name":"グリーン","win_team_mvp":"ウー!ハーッ!"},{"win_team_name":"グリーン","win_team_mvp":"tatsu"},{"win_team_name":"グリーン","win_team_mvp":"にしん"},{"win_team_name":"グリーン","win_team_mvp":"ryuki"},{"win_team_name":"グリーン","win_team_mvp":"カララギマンゴー"},{"win_team_name":"グリーン","win_team_mvp":"しらすタピオカずし"},{"win_team_name":"グリーン","win_team_mvp":"すい"},{"win_team_name":"レッド","win_team_mvp":"AOT_Lammy"},{"win_team_name":"レッド","win_team_mvp":"◆NS◆JHSれな♪"},{"win_team_name":"グリーン","win_team_mvp":"ノース"},{"win_team_name":"グリーン","win_team_mvp":"ななまつgirl"},{"win_team_name":"レッド","win_team_mvp":"ぼくだ~れだ!"},{"win_team_name":"グリーン","win_team_mvp":"だ～しゅ"},{"win_team_name":"グリーン","win_team_mvp":"きいろい　ね☆ず☆み"},{"win_team_name":"グリーン","win_team_mvp":"たこやき仝Yuo6"},{"win_team_name":"レッド","win_team_mvp":"ばあむ"},{"win_team_name":"グリーン","win_team_mvp":"ドワーフ"},{"win_team_name":"レッド","win_team_mvp":"トッポ"},{"win_team_name":"グリーン","win_team_mvp":"Hイカる"},{"win_team_name":"レッド","win_team_mvp":"はこ"},{"win_team_name":"グリーン","win_team_mvp":"きりすず.BB"},{"win_team_name":"グリーン","win_team_mvp":"〆PTRC_あひるβ"},{"win_team_name":"グリーン","win_team_mvp":"YD_まっcha"},{"win_team_name":"レッド","win_team_mvp":"カイウス"},{"win_team_name":"グリーン","win_team_mvp":"1032"},{"win_team_name":"グリーン","win_team_mvp":"きょう、かいました。"},{"win_team_name":"レッド","win_team_mvp":"ゆうと"},{"win_team_name":"グリーン","win_team_mvp":"へりー、"},{"win_team_name":"レッド","win_team_mvp":"だいちゃんだお"},{"win_team_name":"グリーン","win_team_mvp":"かまぼこ"},{"win_team_name":"グリーン","win_team_mvp":"カノー#Isis"},{"win_team_name":"レッド","win_team_mvp":"ばんび"},{"win_team_name":"レッド","win_team_mvp":"☆けい☆"},{"win_team_name":"レッド","win_team_mvp":"はるく"},{"win_team_name":"グリーン","win_team_mvp":"するめ"},{"win_team_name":"レッド","win_team_mvp":"　　　　　　　　　　"},{"win_team_name":"レッド","win_team_mvp":"さとみ"},{"win_team_name":"グリーン","win_team_mvp":"かみむしゃいっしー"},{"win_team_name":"グリーン","win_team_mvp":"[GES]łøνē♪"},{"win_team_name":"グリーン","win_team_mvp":"ワタル"},{"win_team_name":"グリーン","win_team_mvp":"もちごめ"},{"win_team_name":"レッド","win_team_mvp":"シロウ"},{"win_team_name":"グリーン","win_team_mvp":"【SFC】スバル"},{"win_team_name":"グリーン","win_team_mvp":"うぽ"},{"win_team_name":"レッド","win_team_mvp":"RYOratoon"},{"win_team_name":"グリーン","win_team_mvp":"マサト"},{"win_team_name":"グリーン","win_team_mvp":"こしやまたけとともに"},{"win_team_name":"グリーン","win_team_mvp":"そりゃそうじゃ"},{"win_team_name":"グリーン","win_team_mvp":"RU-TAKE"},{"win_team_name":"グリーン","win_team_mvp":"ゲソにぃのいもうと。"},{"win_team_name":"グリーン","win_team_mvp":"せんだいしみん"},{"win_team_name":"レッド","win_team_mvp":"ゆうこ"},{"win_team_name":"グリーン","win_team_mvp":"クリリンのことかー!"},{"win_team_name":"グリーン","win_team_mvp":"R-ta"},{"win_team_name":"グリーン","win_team_mvp":"やきサケ"},{"win_team_name":"グリーン","win_team_mvp":"なぐさ_NfRs"},{"win_team_name":"グリーン","win_team_mvp":"てぃーや#といろ"},{"win_team_name":"グリーン","win_team_mvp":"かなめ"},{"win_team_name":"レッド","win_team_mvp":"かずま"},{"win_team_name":"グリーン","win_team_mvp":"S"},{"win_team_name":"レッド","win_team_mvp":"ゆう"},{"win_team_name":"グリーン","win_team_mvp":"いちる"},{"win_team_name":"グリーン","win_team_mvp":"ちよ"},{"win_team_name":"レッド","win_team_mvp":"しんげきのハムスター"},{"win_team_name":"レッド","win_team_mvp":"れいや"},{"win_team_name":"グリーン","win_team_mvp":"モロロン"},{"win_team_name":"レッド","win_team_mvp":"わたあめ"},{"win_team_name":"グリーン","win_team_mvp":"ともや"},{"win_team_name":"グリーン","win_team_mvp":"YTR"}]